apigateway/__init__.py
apigateway/admin.py
apigateway/apps.py
apigateway/models.py
apigateway/tests.py
apigateway/urls.py
apigateway/views.py
apigateway/migrations/0001_initial.py
apigateway/migrations/0002_auto_20190221_1755.py
apigateway/migrations/__init__.py
zuul/__init__.py
zuul/settings.py
zuul/urls.py
zuul/wsgi.py
django_zuul-1.0.1.dist-info/METADATA
django_zuul-1.0.1.dist-info/WHEEL
django_zuul-1.0.1.dist-info/top_level.txt
django_zuul-1.0.1.dist-info/RECORD
